MANIFEST.in
README.rst
setup.py
geekcms/__init__.py
geekcms/doc_construct.py
geekcms/download_theme.py
geekcms/interface.py
geekcms/loadup.py
geekcms/protocol.py
geekcms/sequence_analyze.py
geekcms/utils.py
geekcms.egg-info/PKG-INFO
geekcms.egg-info/SOURCES.txt
geekcms.egg-info/dependency_links.txt
geekcms.egg-info/entry_points.txt
geekcms.egg-info/requires.txt
geekcms.egg-info/top_level.txt
geekcms/parser/__init__.py
geekcms/parser/simple_lex.py
geekcms/parser/simple_yacc.py
geekcms/parser/utils.py
tests/__init__.py
tests/load_tests.py
tests/test_doc.py
tests/test_loadup.py
tests/test_main.py
tests/test_parser.py
tests/test_protocol.py
tests/test_utils.py
tests/cases/loader/case1
tests/cases/loader/case2
tests/cases/parser/case1
tests/cases/parser/case2
tests/cases/parser/case3
tests/cases/parser/case4
tests/cases/parser/case5
tests/cases/parser/case6
tests/cases/project/settings
tests/cases/project/themes/test_theme1/__init__.py
tests/cases/project/themes/test_theme1/plugin.py
tests/cases/project/themes/test_theme1/settings
tests/cases/project/themes/test_theme2/__init__.py
tests/cases/project/themes/test_theme2/plugin.py
tests/cases/project/themes/test_theme2/settings