Metadata-Version: 1.1
Name: geekcms
Version: 0.3
Summary: a lightweight framework for static site development.
Home-page: https://github.com/haoxun/GeekCMS
Author: Zhan Haoxun
Author-email: programmer.zhx@gmail.com
License: MIT
Platform: UNKNOWN
Classifier: Development Status :: 3 - Alpha
Classifier: Programming Language :: Python :: 3.3
Classifier: Operating System :: OS Independent
Classifier: License :: OSI Approved :: MIT License
